{"2526.1": {"municipio": "80101", "recinto": "U.E. Liceo Mario Saielly", "voto_valido": 546, "voto_blanco": 8, "voto_nulo": 36, "voto_emitido": 590, "validos": 0.9254, "habilitados": 742, "ganador": 0.5623, "x": -64.90276, "y": -14.83593}, "2526.10": {"municipio": "80101", "recinto": "U.E. Hormando Ortiz Chávez", "voto_valido": 542, "voto_blanco": 5, "voto_nulo": 24, "voto_emitido": 571, "validos": 0.9492, "habilitados": 717, "ganador": 0.6513, "x": -64.90439, "y": -14.82626}, "2526.11": {"municipio": "80101", "recinto": "U.E. San Vicente", "voto_valido": 2384, "voto_blanco": 12, "voto_nulo": 109, "voto_emitido": 2505, "validos": 0.9517, "habilitados": 3104, "ganador": 0.6166, "x": -64.91093, "y": -14.8346}, "2526.13": {"municipio": "80101", "recinto": "U.E.  Emilio Campos Pedriel", "voto_valido": 2267, "voto_blanco": 20, "voto_nulo": 93, "voto_emitido": 2380, "validos": 0.9525, "habilitados": 2908, "ganador": 0.6228, "x": -64.8847, "y": -14.81962}, "2526.14": {"municipio": "80101", "recinto": "U.E. J.Azurduy De Padilla", "voto_valido": 1026, "voto_blanco": 9, "voto_nulo": 50, "voto_emitido": 1085, "validos": 0.9456, "habilitados": 1311, "ganador": 0.6384, "x": -64.8893, "y": -14.82634}, "2526.15": {"municipio": "80101", "recinto": "U.E. 4 De  Febrero", "voto_valido": 2919, "voto_blanco": 30, "voto_nulo": 198, "voto_emitido": 3147, "validos": 0.9276, "habilitados": 3973, "ganador": 0.5214, "x": -64.90131, "y": -14.84447}, "2526.16": {"municipio": "80101", "recinto": "(Cárcel) Cárcel Mocobi", "voto_valido": 228, "voto_blanco": 1, "voto_nulo": 16, "voto_emitido": 245, "validos": 0.9306, "habilitados": 348, "ganador": 0.6096, "x": -64.90376, "y": -14.77958}, "2526.18": {"municipio": "80101", "recinto": "U.E. La Salle", "voto_valido": 1390, "voto_blanco": 16, "voto_nulo": 64, "voto_emitido": 1470, "validos": 0.9456, "habilitados": 1870, "ganador": 0.641, "x": -64.89569, "y": -14.82676}, "2526.19": {"municipio": "80101", "recinto": "U.E. Mary Ribera G.", "voto_valido": 2731, "voto_blanco": 18, "voto_nulo": 132, "voto_emitido": 2881, "validos": 0.9479, "habilitados": 3451, "ganador": 0.5873, "x": -64.88783, "y": -14.81399}, "2526.2": {"municipio": "80101", "recinto": "U.E. Nicolas Suarez", "voto_valido": 1051, "voto_blanco": 7, "voto_nulo": 53, "voto_emitido": 1111, "validos": 0.946, "habilitados": 1439, "ganador": 0.667, "x": -64.90492, "y": -14.83268}, "2526.20": {"municipio": "80101", "recinto": "U.E. Corina Hurtado De", "voto_valido": 2156, "voto_blanco": 23, "voto_nulo": 141, "voto_emitido": 2320, "validos": 0.9293, "habilitados": 2837, "ganador": 0.5376, "x": -64.89422, "y": -14.84378}, "2526.24": {"municipio": "80101", "recinto": "U.E. Nuestra Señora de Fátima", "voto_valido": 1762, "voto_blanco": 13, "voto_nulo": 83, "voto_emitido": 1858, "validos": 0.9483, "habilitados": 2338, "ganador": 0.6277, "x": -64.89811, "y": -14.83099}, "2526.25027": {"municipio": "80101", "recinto": "U.E. Joaquín Hurtado Chavez", "voto_valido": 1775, "voto_blanco": 18, "voto_nulo": 88, "voto_emitido": 1881, "validos": 0.9436, "habilitados": 2379, "ganador": 0.4901, "x": -64.90425, "y": -14.81511}, "2526.25028": {"municipio": "80101", "recinto": "U.E. Orlando Monasterio Claure", "voto_valido": 431, "voto_blanco": 6, "voto_nulo": 25, "voto_emitido": 462, "validos": 0.9329, "habilitados": 554, "ganador": 0.5012, "x": -64.93098, "y": -14.8181}, "2526.25029": {"municipio": "80101", "recinto": "U.A.B. (Carrera de Derecho)", "voto_valido": 2654, "voto_blanco": 14, "voto_nulo": 126, "voto_emitido": 2794, "validos": 0.9499, "habilitados": 3400, "ganador": 0.6292, "x": -64.91308, "y": -14.83274}, "2526.25030": {"municipio": "80101", "recinto": "U.E. 15 de Agosto", "voto_valido": 1912, "voto_blanco": 21, "voto_nulo": 91, "voto_emitido": 2024, "validos": 0.9447, "habilitados": 2530, "ganador": 0.5445, "x": -64.92943, "y": -14.83425}, "2526.25031": {"municipio": "80101", "recinto": "U.E. Luis Espinal Cams", "voto_valido": 1512, "voto_blanco": 20, "voto_nulo": 115, "voto_emitido": 1647, "validos": 0.918, "habilitados": 2151, "ganador": 0.4563, "x": -64.92507, "y": -14.84091}, "2526.25032": {"municipio": "80101", "recinto": "U.E. Gonzalo Suarez D.", "voto_valido": 689, "voto_blanco": 10, "voto_nulo": 46, "voto_emitido": 745, "validos": 0.9248, "habilitados": 989, "ganador": 0.5167, "x": -64.90136, "y": -14.85325}, "2526.25033": {"municipio": "80101", "recinto": "U.E. Los Cedros", "voto_valido": 1099, "voto_blanco": 10, "voto_nulo": 39, "voto_emitido": 1148, "validos": 0.9573, "habilitados": 1483, "ganador": 0.6597, "x": -64.90415, "y": -14.82387}, "2526.26": {"municipio": "80101", "recinto": "U.E.  Nueva Trinidad", "voto_valido": 2798, "voto_blanco": 43, "voto_nulo": 177, "voto_emitido": 3018, "validos": 0.9271, "habilitados": 3906, "ganador": 0.5247, "x": -64.8754, "y": -14.82357}, "2526.26180": {"municipio": "80101", "recinto": "U.E. La Palmera", "voto_valido": 856, "voto_blanco": 9, "voto_nulo": 33, "voto_emitido": 898, "validos": 0.9532, "habilitados": 1018, "ganador": 0.653, "x": -64.89687, "y": -14.79046}, "2526.27": {"municipio": "80101", "recinto": "U.E. Villa Vecinal", "voto_valido": 2639, "voto_blanco": 23, "voto_nulo": 136, "voto_emitido": 2798, "validos": 0.9432, "habilitados": 3496, "ganador": 0.5794, "x": -64.87392, "y": -14.81023}, "2526.29": {"municipio": "80101", "recinto": "(Cárcel) Cárcel De Mujeres", "voto_valido": 52, "voto_blanco": 2, "voto_nulo": 0, "voto_emitido": 54, "validos": 0.963, "habilitados": 68, "ganador": 0.3654, "x": -64.90281, "y": -14.84692}, "2526.30": {"municipio": "80101", "recinto": "U.E. San Francisco De Asís", "voto_valido": 704, "voto_blanco": 7, "voto_nulo": 16, "voto_emitido": 727, "validos": 0.9684, "habilitados": 841, "ganador": 0.7131, "x": -64.88588, "y": -14.82278}, "2526.31": {"municipio": "80101", "recinto": "U.E. Mangalito", "voto_valido": 1443, "voto_blanco": 23, "voto_nulo": 92, "voto_emitido": 1558, "validos": 0.9262, "habilitados": 1952, "ganador": 0.5572, "x": -64.91572, "y": -14.84847}, "2526.32": {"municipio": "80101", "recinto": "U.E.  Gral. Hugo Banzer Suarez", "voto_valido": 385, "voto_blanco": 4, "voto_nulo": 23, "voto_emitido": 412, "validos": 0.9345, "habilitados": 532, "ganador": 0.626, "x": -64.9059, "y": -14.77769}, "2526.32003": {"municipio": "80101", "recinto": "U.A.B. Medicina", "voto_valido": 946, "voto_blanco": 10, "voto_nulo": 38, "voto_emitido": 994, "validos": 0.9517, "habilitados": 1230, "ganador": 0.6247, "x": -64.9003, "y": -14.83146}, "2526.32005": {"municipio": "80101", "recinto": "Palacio de los Deportes Trinidad", "voto_valido": 716, "voto_blanco": 7, "voto_nulo": 58, "voto_emitido": 781, "validos": 0.9168, "habilitados": 952, "ganador": 0.4902, "x": -64.90587, "y": -14.8375}, "2526.32007": {"municipio": "80101", "recinto": "U.E. Kinder República Argentina", "voto_valido": 491, "voto_blanco": 3, "voto_nulo": 38, "voto_emitido": 532, "validos": 0.9229, "habilitados": 645, "ganador": 0.6253, "x": -64.90282, "y": -14.83462}, "2526.32008": {"municipio": "80101", "recinto": "U.E. Metodista Instituto Americano Trinidad", "voto_valido": 660, "voto_blanco": 3, "voto_nulo": 28, "voto_emitido": 691, "validos": 0.9551, "habilitados": 898, "ganador": 0.6682, "x": -64.90432, "y": -14.83349}, "2526.32009": {"municipio": "80101", "recinto": "U.E. Andrés Bello", "voto_valido": 415, "voto_blanco": 5, "voto_nulo": 18, "voto_emitido": 438, "validos": 0.9475, "habilitados": 563, "ganador": 0.6458, "x": -64.90421, "y": -14.82581}, "2526.32010": {"municipio": "80101", "recinto": "U.E. Christa Mc Auliffe", "voto_valido": 904, "voto_blanco": 9, "voto_nulo": 29, "voto_emitido": 942, "validos": 0.9597, "habilitados": 1182, "ganador": 0.6007, "x": -64.90945, "y": -14.83611}, "2526.32011": {"municipio": "80101", "recinto": "U.E. Evangélico Cuatro", "voto_valido": 626, "voto_blanco": 2, "voto_nulo": 22, "voto_emitido": 650, "validos": 0.9631, "habilitados": 797, "ganador": 0.615, "x": -64.89097, "y": -14.82631}, "2526.32012": {"municipio": "80101", "recinto": "U.E.Inmaculada", "voto_valido": 1871, "voto_blanco": 20, "voto_nulo": 128, "voto_emitido": 2019, "validos": 0.9267, "habilitados": 2466, "ganador": 0.5313, "x": -64.87007, "y": -14.81885}, "2526.32013": {"municipio": "80101", "recinto": "E. S. F. M. Clara Parada de Pinto", "voto_valido": 1431, "voto_blanco": 18, "voto_nulo": 78, "voto_emitido": 1527, "validos": 0.9371, "habilitados": 1908, "ganador": 0.6226, "x": -64.88401, "y": -14.8135}, "2526.32014": {"municipio": "80101", "recinto": "U.E. Jesús Rioja Aponte", "voto_valido": 2134, "voto_blanco": 25, "voto_nulo": 112, "voto_emitido": 2271, "validos": 0.9397, "habilitados": 2694, "ganador": 0.5281, "x": -64.86979, "y": -14.80542}, "2526.32147": {"municipio": "80101", "recinto": "U.E.Villa Magdalena", "voto_valido": 1014, "voto_blanco": 8, "voto_nulo": 58, "voto_emitido": 1080, "validos": 0.9389, "habilitados": 1286, "ganador": 0.5858, "x": -64.9112, "y": -14.8144}, "2526.32148": {"municipio": "80101", "recinto": "U.E.Villa Marin", "voto_valido": 1148, "voto_blanco": 14, "voto_nulo": 80, "voto_emitido": 1242, "validos": 0.9243, "habilitados": 1631, "ganador": 0.5078, "x": -64.9309, "y": -14.844}, "2526.32150": {"municipio": "80101", "recinto": "U.E. Nacional 6 de Agosto", "voto_valido": 1056, "voto_blanco": 10, "voto_nulo": 45, "voto_emitido": 1111, "validos": 0.9505, "habilitados": 1356, "ganador": 0.6364, "x": -64.8991, "y": -14.8152}, "2526.32370": {"municipio": "80101", "recinto": "U.E. Hernán Melgar Justiniano", "voto_valido": 182, "voto_blanco": 2, "voto_nulo": 10, "voto_emitido": 194, "validos": 0.9381, "habilitados": 230, "ganador": 0.4835, "x": -64.90716, "y": -14.84765}, "2526.40": {"municipio": "80101", "recinto": "U.E.  13 de Abril", "voto_valido": 3202, "voto_blanco": 40, "voto_nulo": 186, "voto_emitido": 3428, "validos": 0.9341, "habilitados": 4260, "ganador": 0.5278, "x": -64.88435, "y": -14.83625}, "2526.5": {"municipio": "80101", "recinto": "U.E. J. Chavez Suarez", "voto_valido": 3334, "voto_blanco": 38, "voto_nulo": 189, "voto_emitido": 3561, "validos": 0.9363, "habilitados": 4472, "ganador": 0.5405, "x": -64.90463, "y": -14.8414}, "2526.6": {"municipio": "80101", "recinto": "U.E. Pedro Ignacio Muiba", "voto_valido": 2115, "voto_blanco": 24, "voto_nulo": 129, "voto_emitido": 2268, "validos": 0.9325, "habilitados": 2884, "ganador": 0.5565, "x": -64.91414, "y": -14.84481}, "2526.7": {"municipio": "80101", "recinto": "U.E. San Antonio", "voto_valido": 1810, "voto_blanco": 16, "voto_nulo": 112, "voto_emitido": 1938, "validos": 0.934, "habilitados": 2353, "ganador": 0.6028, "x": -64.91032, "y": -14.83844}, "2526.8": {"municipio": "80101", "recinto": "U.E. Raúl Monje Roca", "voto_valido": 1888, "voto_blanco": 15, "voto_nulo": 84, "voto_emitido": 1987, "validos": 0.9502, "habilitados": 2376, "ganador": 0.6398, "x": -64.8938, "y": -14.83707}, "2526.9": {"municipio": "80101", "recinto": "U.E. J. Lorenzo Campero", "voto_valido": 1119, "voto_blanco": 7, "voto_nulo": 59, "voto_emitido": 1185, "validos": 0.9443, "habilitados": 1429, "ganador": 0.6577, "x": -64.89998, "y": -14.8257}, "2527.1": {"municipio": "80101", "recinto": "Esc. Loma Suarez", "voto_valido": 477, "voto_blanco": 5, "voto_nulo": 50, "voto_emitido": 532, "validos": 0.8966, "habilitados": 828, "ganador": 0.6394, "x": -64.96272, "y": -14.76063}, "2528.1": {"municipio": "80101", "recinto": "Esc. Puerto Ballivian", "voto_valido": 145, "voto_blanco": 3, "voto_nulo": 3, "voto_emitido": 151, "validos": 0.9603, "habilitados": 186, "ganador": 0.6, "x": -64.97205, "y": -14.79312}, "2529.1": {"municipio": "80101", "recinto": "Esc. Mayor Pedro Vaca Diez", "voto_valido": 334, "voto_blanco": 5, "voto_nulo": 27, "voto_emitido": 366, "validos": 0.9126, "habilitados": 475, "ganador": 0.5599, "x": -64.96582, "y": -14.86952}, "2530.2": {"municipio": "80102", "recinto": "Escuela San Javier", "voto_valido": 485, "voto_blanco": 8, "voto_nulo": 14, "voto_emitido": 507, "validos": 0.9566, "habilitados": 726, "ganador": 0.4454, "x": -64.88087, "y": -14.59987}, "2532.2": {"municipio": "80102", "recinto": "Escuela Espiritu Santo", "voto_valido": 38, "voto_blanco": 1, "voto_nulo": 3, "voto_emitido": 42, "validos": 0.9048, "habilitados": 66, "ganador": 0.3684, "x": -64.80295, "y": -14.63469}, "2534.1": {"municipio": "80101", "recinto": "Esc. San Juan De Aguas Dulces", "voto_valido": 106, "voto_blanco": 0, "voto_nulo": 5, "voto_emitido": 111, "validos": 0.955, "habilitados": 132, "ganador": 0.783, "x": -64.57809, "y": -14.80817}, "2535.2": {"municipio": "80102", "recinto": "Escuela San Pedro", "voto_valido": 347, "voto_blanco": 5, "voto_nulo": 18, "voto_emitido": 370, "validos": 0.9378, "habilitados": 484, "ganador": 0.7925, "x": -64.90086, "y": -14.33668}, "2539.2": {"municipio": "80102", "recinto": "Escuela Nueva Israel", "voto_valido": 574, "voto_blanco": 10, "voto_nulo": 39, "voto_emitido": 623, "validos": 0.9213, "habilitados": 906, "ganador": 0.5017, "x": -64.3349, "y": -14.6718}, "2540.1": {"municipio": "80201", "recinto": "U.E. San Jose Obrero", "voto_valido": 1874, "voto_blanco": 41, "voto_nulo": 166, "voto_emitido": 2081, "validos": 0.9005, "habilitados": 2900, "ganador": 0.5181, "x": -66.06607, "y": -10.99754}, "2540.10": {"municipio": "80201", "recinto": "U.E.Jhon Fitzgerald Kennedy", "voto_valido": 1181, "voto_blanco": 11, "voto_nulo": 68, "voto_emitido": 1260, "validos": 0.9373, "habilitados": 1531, "ganador": 0.5148, "x": -66.06571, "y": -10.99814}, "2540.11": {"municipio": "80201", "recinto": "U.E.  Británica", "voto_valido": 1979, "voto_blanco": 36, "voto_nulo": 172, "voto_emitido": 2187, "validos": 0.9049, "habilitados": 2815, "ganador": 0.4901, "x": -66.05006, "y": -11.01523}, "2540.12": {"municipio": "80201", "recinto": "U.E. Petrolera", "voto_valido": 2773, "voto_blanco": 51, "voto_nulo": 228, "voto_emitido": 3052, "validos": 0.9086, "habilitados": 3807, "ganador": 0.4919, "x": -66.05014, "y": -11.00229}, "2540.13": {"municipio": "80201", "recinto": "U.E.  Eduardo Abaroa", "voto_valido": 2382, "voto_blanco": 36, "voto_nulo": 124, "voto_emitido": 2542, "validos": 0.9371, "habilitados": 3257, "ganador": 0.5122, "x": -66.06204, "y": -11.00703}, "2540.14": {"municipio": "80201", "recinto": "U.E.  1ro. de Diciembre", "voto_valido": 1776, "voto_blanco": 28, "voto_nulo": 143, "voto_emitido": 1947, "validos": 0.9122, "habilitados": 2548, "ganador": 0.4837, "x": -66.07318, "y": -11.01311}, "2540.15": {"municipio": "80201", "recinto": "U.E. Los Tajibos", "voto_valido": 2945, "voto_blanco": 76, "voto_nulo": 295, "voto_emitido": 3316, "validos": 0.8881, "habilitados": 4495, "ganador": 0.4896, "x": -66.04456, "y": -11.02086}, "2540.16": {"municipio": "80201", "recinto": "U.E. Nuestra Señora Del Carmen", "voto_valido": 1251, "voto_blanco": 11, "voto_nulo": 79, "voto_emitido": 1341, "validos": 0.9329, "habilitados": 1745, "ganador": 0.5428, "x": -66.07724, "y": -10.99875}, "2540.17": {"municipio": "80201", "recinto": "Unidad Educativa Nataniel García Chavez", "voto_valido": 1858, "voto_blanco": 44, "voto_nulo": 120, "voto_emitido": 2022, "validos": 0.9189, "habilitados": 2581, "ganador": 0.479, "x": -66.07935, "y": -11.00858}, "2540.18": {"municipio": "80201", "recinto": "(Cárcel) Penal Riberalta", "voto_valido": 21, "voto_blanco": 3, "voto_nulo": 7, "voto_emitido": 31, "validos": 0.6774, "habilitados": 102, "ganador": 0.4762, "x": -66.0738, "y": -10.99669}, "2540.19": {"municipio": "80201", "recinto": "U.E.  San Francisco", "voto_valido": 610, "voto_blanco": 6, "voto_nulo": 36, "voto_emitido": 652, "validos": 0.9356, "habilitados": 874, "ganador": 0.5754, "x": -66.07206, "y": -11.00753}, "2540.20": {"municipio": "80201", "recinto": "U.E.  Walter Alpire Duran", "voto_valido": 1239, "voto_blanco": 23, "voto_nulo": 106, "voto_emitido": 1368, "validos": 0.9057, "habilitados": 1734, "ganador": 0.544, "x": -66.05729, "y": -11.01164}, "2540.21": {"municipio": "80201", "recinto": "U.E.  Ismael Carrasco Telleria", "voto_valido": 1452, "voto_blanco": 34, "voto_nulo": 161, "voto_emitido": 1647, "validos": 0.8816, "habilitados": 2090, "ganador": 0.5083, "x": -66.05402, "y": -11.01021}, "2540.22": {"municipio": "80201", "recinto": "U.E. Federico Demmer", "voto_valido": 1812, "voto_blanco": 31, "voto_nulo": 140, "voto_emitido": 1983, "validos": 0.9138, "habilitados": 2681, "ganador": 0.5348, "x": -66.04344, "y": -10.99968}, "2540.23": {"municipio": "80201", "recinto": "U.E.  San Juan", "voto_valido": 2820, "voto_blanco": 98, "voto_nulo": 314, "voto_emitido": 3232, "validos": 0.8725, "habilitados": 4335, "ganador": 0.522, "x": -66.04671, "y": -11.03188}, "2540.25574": {"municipio": "80201", "recinto": "U.E. Litoral", "voto_valido": 3125, "voto_blanco": 59, "voto_nulo": 265, "voto_emitido": 3449, "validos": 0.9061, "habilitados": 4583, "ganador": 0.5082, "x": -66.03361, "y": -11.00029}, "2540.26355": {"municipio": "80201", "recinto": "U.E. 21 de Septiembre", "voto_valido": 2208, "voto_blanco": 54, "voto_nulo": 265, "voto_emitido": 2527, "validos": 0.8738, "habilitados": 3346, "ganador": 0.505, "x": -66.03877, "y": -11.03985}, "2540.26356": {"municipio": "80201", "recinto": "U.E. Barbarita Paz Yamane", "voto_valido": 1093, "voto_blanco": 34, "voto_nulo": 97, "voto_emitido": 1224, "validos": 0.893, "habilitados": 1633, "ganador": 0.4849, "x": -66.05606, "y": -11.0183}, "2540.26357": {"municipio": "80201", "recinto": "U.E. Polo Palacios", "voto_valido": 935, "voto_blanco": 9, "voto_nulo": 60, "voto_emitido": 1004, "validos": 0.9313, "habilitados": 1313, "ganador": 0.5027, "x": -66.0798, "y": -11.0031}, "2540.26358": {"municipio": "80201", "recinto": "U.E. Guido Gutierrez Moreno", "voto_valido": 721, "voto_blanco": 21, "voto_nulo": 89, "voto_emitido": 831, "validos": 0.8676, "habilitados": 1160, "ganador": 0.516, "x": -66.04907, "y": -11.00751}, "2540.3": {"municipio": "80201", "recinto": "U.E. Felix Sattory Roman", "voto_valido": 1905, "voto_blanco": 34, "voto_nulo": 114, "voto_emitido": 2053, "validos": 0.9279, "habilitados": 2599, "ganador": 0.5045, "x": -66.06739, "y": -11.00182}, "2540.32016": {"municipio": "80201", "recinto": "U.E. Arca Maranatha", "voto_valido": 957, "voto_blanco": 16, "voto_nulo": 61, "voto_emitido": 1034, "validos": 0.9255, "habilitados": 1259, "ganador": 0.5684, "x": -66.06692, "y": -11.00104}, "2540.32119": {"municipio": "80201", "recinto": "(Cárcel) Penal Nuevo Riberalta", "voto_valido": 77, "voto_blanco": 5, "voto_nulo": 4, "voto_emitido": 86, "validos": 0.8953, "habilitados": 121, "ganador": 0.3896, "x": -66.03582, "y": -11.01168}, "2540.4": {"municipio": "80201", "recinto": "Politecnico Benjamin Bowles", "voto_valido": 1915, "voto_blanco": 41, "voto_nulo": 192, "voto_emitido": 2148, "validos": 0.8915, "habilitados": 2753, "ganador": 0.4715, "x": -66.05167, "y": -11.00485}, "2540.6": {"municipio": "80201", "recinto": "U.E. Juana Azurduy De Padilla", "voto_valido": 644, "voto_blanco": 9, "voto_nulo": 66, "voto_emitido": 719, "validos": 0.8957, "habilitados": 991, "ganador": 0.5466, "x": -66.07388, "y": -10.99538}, "2540.8": {"municipio": "80201", "recinto": "U.E. 6 de Junio", "voto_valido": 1135, "voto_blanco": 11, "voto_nulo": 53, "voto_emitido": 1199, "validos": 0.9466, "habilitados": 1705, "ganador": 0.526, "x": -66.077, "y": -11.00458}, "2540.9": {"municipio": "80201", "recinto": "U.E. Nacional Pedro Kramer", "voto_valido": 963, "voto_blanco": 21, "voto_nulo": 44, "voto_emitido": 1028, "validos": 0.9368, "habilitados": 1340, "ganador": 0.5566, "x": -66.06915, "y": -10.99869}, "2542.1": {"municipio": "80301", "recinto": "Esc. Peña Amarilla", "voto_valido": 78, "voto_blanco": 0, "voto_nulo": 4, "voto_emitido": 82, "validos": 0.9512, "habilitados": 109, "ganador": 0.3077, "x": -66.67179, "y": -11.5471}, "2543.1": {"municipio": "80201", "recinto": "Escuela Nazareth", "voto_valido": 102, "voto_blanco": 3, "voto_nulo": 17, "voto_emitido": 122, "validos": 0.8361, "habilitados": 155, "ganador": 0.4608, "x": -66.3375, "y": -11.38739}, "2546.1": {"municipio": "80201", "recinto": "U.E. Zaida Gosalvez Alarcón", "voto_valido": 255, "voto_blanco": 12, "voto_nulo": 20, "voto_emitido": 287, "validos": 0.8885, "habilitados": 358, "ganador": 0.3176, "x": -66.16624, "y": -11.14738}, "2548.1": {"municipio": "80202", "recinto": "Esc. Antofagasta", "voto_valido": 75, "voto_blanco": 3, "voto_nulo": 3, "voto_emitido": 81, "validos": 0.9259, "habilitados": 110, "ganador": 0.3867, "x": -65.39104, "y": -10.39382}, "2549.1": {"municipio": "80202", "recinto": "Esc. Juddi De Suarez", "voto_valido": 303, "voto_blanco": 64, "voto_nulo": 12, "voto_emitido": 379, "validos": 0.7995, "habilitados": 424, "ganador": 0.3366, "x": -65.58167, "y": -10.53687}, "2551.1": {"municipio": "80202", "recinto": "Esc. Rosario Del Yata", "voto_valido": 288, "voto_blanco": 0, "voto_nulo": 22, "voto_emitido": 310, "validos": 0.929, "habilitados": 422, "ganador": 0.4306, "x": -65.57995, "y": -10.99195}, "2555.1": {"municipio": "80301", "recinto": "U.E. Rene Barrientos Ortuño", "voto_valido": 640, "voto_blanco": 5, "voto_nulo": 26, "voto_emitido": 671, "validos": 0.9538, "habilitados": 934, "ganador": 0.3578, "x": -67.33835, "y": -14.29512}, "2555.2": {"municipio": "80301", "recinto": "U.E. Nacional de Reyes", "voto_valido": 1375, "voto_blanco": 9, "voto_nulo": 47, "voto_emitido": 1431, "validos": 0.9609, "habilitados": 1909, "ganador": 0.4262, "x": -67.33482, "y": -14.29558}, "2555.3": {"municipio": "80301", "recinto": "U.E. Jesus Alvarez Rodriguez", "voto_valido": 1550, "voto_blanco": 19, "voto_nulo": 56, "voto_emitido": 1625, "validos": 0.9538, "habilitados": 2130, "ganador": 0.4039, "x": -67.3343, "y": -14.29483}, "2559.1": {"municipio": "80302", "recinto": "U.E. San Francisco De Borja", "voto_valido": 1395, "voto_blanco": 20, "voto_nulo": 59, "voto_emitido": 1474, "validos": 0.9464, "habilitados": 1893, "ganador": 0.6186, "x": -66.75023, "y": -14.85829}, "2559.2": {"municipio": "80302", "recinto": "U.E. German Busch", "voto_valido": 1672, "voto_blanco": 18, "voto_nulo": 75, "voto_emitido": 1765, "validos": 0.9473, "habilitados": 2249, "ganador": 0.6202, "x": -66.74983, "y": -14.85664}, "2559.25860": {"municipio": "80302", "recinto": "U.E. Cochabamba", "voto_valido": 1401, "voto_blanco": 16, "voto_nulo": 88, "voto_emitido": 1505, "validos": 0.9309, "habilitados": 1960, "ganador": 0.5717, "x": -66.74444, "y": -14.86279}, "2559.3": {"municipio": "80302", "recinto": "U.E. Arnulfo Martínez", "voto_valido": 1240, "voto_blanco": 21, "voto_nulo": 75, "voto_emitido": 1336, "validos": 0.9281, "habilitados": 1756, "ganador": 0.5452, "x": -66.74274, "y": -14.86135}, "2559.4": {"municipio": "80302", "recinto": "U.E. Villa San Antonio", "voto_valido": 924, "voto_blanco": 11, "voto_nulo": 64, "voto_emitido": 999, "validos": 0.9249, "habilitados": 1328, "ganador": 0.5249, "x": -66.74652, "y": -14.87003}, "2559.5": {"municipio": "80302", "recinto": "U.E. San Ignacio Del Maniqui", "voto_valido": 725, "voto_blanco": 10, "voto_nulo": 45, "voto_emitido": 780, "validos": 0.9295, "habilitados": 1086, "ganador": 0.5655, "x": -66.72903, "y": -14.85899}, "2559.6": {"municipio": "80302", "recinto": "U.E. 18 de Noviembre", "voto_valido": 1479, "voto_blanco": 23, "voto_nulo": 63, "voto_emitido": 1565, "validos": 0.945, "habilitados": 2147, "ganador": 0.6078, "x": -66.75239, "y": -14.86087}, "2560.1": {"municipio": "80302", "recinto": "Esc. Santa Elena del Caripo", "voto_valido": 129, "voto_blanco": 5, "voto_nulo": 2, "voto_emitido": 136, "validos": 0.9485, "habilitados": 165, "ganador": 0.7984, "x": -66.82342, "y": -14.5799}, "2561.1": {"municipio": "80401", "recinto": "Esc. Cec. El Totaisal", "voto_valido": 253, "voto_blanco": 6, "voto_nulo": 23, "voto_emitido": 282, "validos": 0.8972, "habilitados": 423, "ganador": 0.6206, "x": -66.32708, "y": -14.87791}, "2562.1": {"municipio": "80302", "recinto": "Esc. Junrreno", "voto_valido": 57, "voto_blanco": 0, "voto_nulo": 0, "voto_emitido": 57, "validos": 1.0, "habilitados": 73, "ganador": 0.7544, "x": -66.93327, "y": -14.37257}, "2563.26361": {"municipio": "80302", "recinto": "U.E. Yucumo", "voto_valido": 2093, "voto_blanco": 96, "voto_nulo": 447, "voto_emitido": 2636, "validos": 0.794, "habilitados": 3462, "ganador": 0.4663, "x": -67.03511, "y": -15.14394}, "2564.1": {"municipio": "80302", "recinto": "Esc. La Embocada", "voto_valido": 353, "voto_blanco": 4, "voto_nulo": 54, "voto_emitido": 411, "validos": 0.8589, "habilitados": 517, "ganador": 0.5694, "x": -66.86135, "y": -15.04577}, "2565.1": {"municipio": "80302", "recinto": "Esc. El Palmar", "voto_valido": 505, "voto_blanco": 28, "voto_nulo": 179, "voto_emitido": 712, "validos": 0.7093, "habilitados": 879, "ganador": 0.5485, "x": -67.08794, "y": -14.97903}, "2566.1": {"municipio": "80304", "recinto": "Esc. Central Piedras Blancas", "voto_valido": 208, "voto_blanco": 6, "voto_nulo": 95, "voto_emitido": 309, "validos": 0.6731, "habilitados": 384, "ganador": 0.4567, "x": -67.15208, "y": -14.78934}, "2568.1": {"municipio": "80302", "recinto": "Esc. S. Juan Del Remanzo", "voto_valido": 99, "voto_blanco": 0, "voto_nulo": 14, "voto_emitido": 113, "validos": 0.8761, "habilitados": 146, "ganador": 0.8788, "x": -66.5321, "y": -14.67902}, "2569.1": {"municipio": "80302", "recinto": "Esc. La Cruz", "voto_valido": 643, "voto_blanco": 8, "voto_nulo": 79, "voto_emitido": 730, "validos": 0.8808, "habilitados": 929, "ganador": 0.4899, "x": -66.73125, "y": -14.97601}, "2570.1": {"municipio": "80302", "recinto": "U. E. Puerto Yucumo", "voto_valido": 343, "voto_blanco": 4, "voto_nulo": 72, "voto_emitido": 419, "validos": 0.8186, "habilitados": 489, "ganador": 0.6501, "x": -66.92703, "y": -15.19178}, "2571.1": {"municipio": "80302", "recinto": "Esc. El Chacal", "voto_valido": 420, "voto_blanco": 1, "voto_nulo": 53, "voto_emitido": 474, "validos": 0.8861, "habilitados": 547, "ganador": 0.6048, "x": -66.62759, "y": -14.75295}, "2573.1": {"municipio": "80303", "recinto": "U.E. Gerardo Reyes", "voto_valido": 2082, "voto_blanco": 15, "voto_nulo": 91, "voto_emitido": 2188, "validos": 0.9516, "habilitados": 2728, "ganador": 0.5941, "x": -66.79248, "y": -14.07916}, "2573.25859": {"municipio": "80303", "recinto": "U.E. Umbelina Claure de Cuellar", "voto_valido": 1135, "voto_blanco": 13, "voto_nulo": 48, "voto_emitido": 1196, "validos": 0.949, "habilitados": 1660, "ganador": 0.6185, "x": -66.79462, "y": -14.0733}, "2581.1": {"municipio": "80401", "recinto": "U.E. Andrés Alberdi Salegui", "voto_valido": 1882, "voto_blanco": 15, "voto_nulo": 38, "voto_emitido": 1935, "validos": 0.9726, "habilitados": 2671, "ganador": 0.5887, "x": -65.4307, "y": -13.7505}, "2581.2": {"municipio": "80401", "recinto": "U.E. Monseñor Daniel Rivero", "voto_valido": 1355, "voto_blanco": 16, "voto_nulo": 50, "voto_emitido": 1421, "validos": 0.9536, "habilitados": 1856, "ganador": 0.5004, "x": -65.42525, "y": -13.74378}, "2581.25861": {"municipio": "80401", "recinto": "U.E. John Fitzgerald Kennedy", "voto_valido": 584, "voto_blanco": 2, "voto_nulo": 22, "voto_emitido": 608, "validos": 0.9605, "habilitados": 1006, "ganador": 0.6164, "x": -65.42288, "y": -13.73543}, "2581.3": {"municipio": "80401", "recinto": "U.E. Guillermo Searle", "voto_valido": 943, "voto_blanco": 8, "voto_nulo": 30, "voto_emitido": 981, "validos": 0.9613, "habilitados": 1363, "ganador": 0.5493, "x": -65.42456, "y": -13.74432}, "2581.32021": {"municipio": "80401", "recinto": "U.E. Monseñor Carlos Anasagasti Zulueta", "voto_valido": 1110, "voto_blanco": 6, "voto_nulo": 41, "voto_emitido": 1157, "validos": 0.9594, "habilitados": 1640, "ganador": 0.5306, "x": -65.42825, "y": -13.74707}, "2581.32116": {"municipio": "80401", "recinto": "U.E. Antonio Carvalho Urey", "voto_valido": 173, "voto_blanco": 1, "voto_nulo": 7, "voto_emitido": 181, "validos": 0.9558, "habilitados": 259, "ganador": 0.6647, "x": -65.42556, "y": -13.74944}, "2582.1": {"municipio": "80402", "recinto": "Esc. Jose Max Paredes", "voto_valido": 337, "voto_blanco": 10, "voto_nulo": 47, "voto_emitido": 394, "validos": 0.8553, "habilitados": 955, "ganador": 0.1395, "x": null, "y": null}, "2583.1": {"municipio": "80402", "recinto": "Esc. Coquinal", "voto_valido": 120, "voto_blanco": 4, "voto_nulo": 4, "voto_emitido": 128, "validos": 0.9375, "habilitados": 244, "ganador": 0.2917, "x": -65.85875, "y": -12.97027}, "2584.1": {"municipio": "80402", "recinto": "Esc. San Carlos", "voto_valido": 43, "voto_blanco": 1, "voto_nulo": 0, "voto_emitido": 44, "validos": 0.9773, "habilitados": 74, "ganador": 0.3953, "x": -65.70103, "y": -13.23234}, "2585.1": {"municipio": "80402", "recinto": "Esc. El Trompillo", "voto_valido": 7, "voto_blanco": 0, "voto_nulo": 0, "voto_emitido": 7, "validos": 1.0, "habilitados": 21, "ganador": 0.7143, "x": -65.11865, "y": -13.11602}, "2586.1": {"municipio": "80402", "recinto": "Esc. El Motacusal", "voto_valido": 83, "voto_blanco": 0, "voto_nulo": 3, "voto_emitido": 86, "validos": 0.9651, "habilitados": 137, "ganador": 0.4458, "x": -65.4307, "y": -12.91581}, "2587.1": {"municipio": "80401", "recinto": "Esc. Los Montes De Oro", "voto_valido": 4, "voto_blanco": 0, "voto_nulo": 0, "voto_emitido": 4, "validos": 1.0, "habilitados": 18, "ganador": 0.25, "x": -65.8585, "y": -14.33763}, "2596.2": {"municipio": "80501", "recinto": "L. Gilfredo Cortez Candia", "voto_valido": 1561, "voto_blanco": 27, "voto_nulo": 139, "voto_emitido": 1727, "validos": 0.9039, "habilitados": 2285, "ganador": 0.4407, "x": -65.64448, "y": -14.99516}, "2596.26360": {"municipio": "80501", "recinto": "U.E. Estanislau de Marchena", "voto_valido": 1544, "voto_blanco": 32, "voto_nulo": 106, "voto_emitido": 1682, "validos": 0.918, "habilitados": 2199, "ganador": 0.4307, "x": -65.63877, "y": -14.99446}, "2596.32433": {"municipio": "80501", "recinto": "U.E. Sócrates Parada Eguez", "voto_valido": 2110, "voto_blanco": 61, "voto_nulo": 155, "voto_emitido": 2326, "validos": 0.9071, "habilitados": 2994, "ganador": 0.4555, "x": -65.64435, "y": -14.99474}, "2597.1": {"municipio": "80501", "recinto": "Esc. Central San Ignacito", "voto_valido": 10, "voto_blanco": 0, "voto_nulo": 0, "voto_emitido": 10, "validos": 1.0, "habilitados": 12, "ganador": 0.9, "x": -65.64748, "y": -15.4581}, "2598.1": {"municipio": "80501", "recinto": "Esc. Fatima", "voto_valido": 124, "voto_blanco": 1, "voto_nulo": 5, "voto_emitido": 130, "validos": 0.9538, "habilitados": 159, "ganador": 0.5081, "x": -65.34778, "y": -14.91402}, "2600.1": {"municipio": "80501", "recinto": "Esc. La Argentina", "voto_valido": 89, "voto_blanco": 1, "voto_nulo": 12, "voto_emitido": 102, "validos": 0.8725, "habilitados": 121, "ganador": 0.1573, "x": -65.32679, "y": -14.82843}, "2601.1": {"municipio": "80501", "recinto": "Esc. El Desengaño", "voto_valido": 103, "voto_blanco": 0, "voto_nulo": 7, "voto_emitido": 110, "validos": 0.9364, "habilitados": 154, "ganador": 0.6019, "x": -65.44534, "y": -14.27502}, "2602.1": {"municipio": "80502", "recinto": "Esc. Central Santa Rosa", "voto_valido": 106, "voto_blanco": 2, "voto_nulo": 14, "voto_emitido": 122, "validos": 0.8689, "habilitados": 151, "ganador": 0.4434, "x": -65.85181, "y": -15.22264}, "2603.1": {"municipio": "80502", "recinto": "Esc. Sub Central Pueblo Nuevo", "voto_valido": 53, "voto_blanco": 4, "voto_nulo": 3, "voto_emitido": 60, "validos": 0.8833, "habilitados": 84, "ganador": 0.4151, "x": -65.88788, "y": -15.24535}, "2604.1": {"municipio": "80501", "recinto": "Esc. San Francisco", "voto_valido": 185, "voto_blanco": 5, "voto_nulo": 17, "voto_emitido": 207, "validos": 0.8937, "habilitados": 301, "ganador": 0.4973, "x": -65.35629, "y": -15.41029}, "2605.1": {"municipio": "80501", "recinto": "Esc. Ovidio Roca C.", "voto_valido": 407, "voto_blanco": 10, "voto_nulo": 63, "voto_emitido": 480, "validos": 0.8479, "habilitados": 646, "ganador": 0.5995, "x": -65.55151, "y": -15.55553}, "2606.1": {"municipio": "80502", "recinto": "Esc. Monte Grande", "voto_valido": 236, "voto_blanco": 8, "voto_nulo": 34, "voto_emitido": 278, "validos": 0.8489, "habilitados": 352, "ganador": 0.8136, "x": -65.82966, "y": -15.63879}, "2608.1": {"municipio": "80501", "recinto": "Esc. San Jose De Patrocinio", "voto_valido": 29, "voto_blanco": 0, "voto_nulo": 1, "voto_emitido": 30, "validos": 0.9667, "habilitados": 39, "ganador": 0.5862, "x": -65.29938, "y": -15.7724}, "2609.1": {"municipio": "80501", "recinto": "Escuela Santísima Trinidad", "voto_valido": 199, "voto_blanco": 8, "voto_nulo": 24, "voto_emitido": 231, "validos": 0.8615, "habilitados": 300, "ganador": 0.5276, "x": -65.76534, "y": -16.61358}, "2610.1": {"municipio": "80501", "recinto": "Esc. Pto. San Lorenzo", "voto_valido": 82, "voto_blanco": 5, "voto_nulo": 14, "voto_emitido": 101, "validos": 0.8119, "habilitados": 143, "ganador": 0.7073, "x": -65.4773, "y": -15.77166}, "2611.1": {"municipio": "80501", "recinto": "Esc. San Miguelito Isiboro", "voto_valido": 83, "voto_blanco": 3, "voto_nulo": 11, "voto_emitido": 97, "validos": 0.8557, "habilitados": 123, "ganador": 0.6024, "x": -65.44078, "y": -16.52943}, "2612.2": {"municipio": "80701", "recinto": "U.E. Arturo Cuellar Rea", "voto_valido": 1106, "voto_blanco": 7, "voto_nulo": 22, "voto_emitido": 1135, "validos": 0.9744, "habilitados": 1847, "ganador": 0.2016, "x": -64.66712, "y": -13.04514}, "2612.3": {"municipio": "80701", "recinto": "Unidad Educativa 21 de Agosto", "voto_valido": 1099, "voto_blanco": 5, "voto_nulo": 14, "voto_emitido": 1118, "validos": 0.983, "habilitados": 1530, "ganador": 0.2266, "x": -64.6656, "y": -13.04053}, "2616.1": {"municipio": "80702", "recinto": "U.E. Napoleón Añez Ortiz", "voto_valido": 1977, "voto_blanco": 7, "voto_nulo": 39, "voto_emitido": 2023, "validos": 0.9773, "habilitados": 2784, "ganador": 0.6636, "x": -64.61865, "y": -13.26702}, "2617.1": {"municipio": "80702", "recinto": "Esc. El Poyori", "voto_valido": 43, "voto_blanco": 0, "voto_nulo": 0, "voto_emitido": 43, "validos": 1.0, "habilitados": 53, "ganador": 0.5581, "x": -64.42094, "y": -13.00931}, "2618.1": {"municipio": "80703", "recinto": "Esc. Antofagasta", "voto_valido": 208, "voto_blanco": 4, "voto_nulo": 3, "voto_emitido": 215, "validos": 0.9674, "habilitados": 290, "ganador": 0.3894, "x": -65.00496, "y": -12.80045}, "2619.1": {"municipio": "80703", "recinto": "Esc. Santa Rosa", "voto_valido": 147, "voto_blanco": 0, "voto_nulo": 0, "voto_emitido": 147, "validos": 1.0, "habilitados": 197, "ganador": 0.0476, "x": -65.11021, "y": -12.29405}, "2620.1": {"municipio": "80701", "recinto": "Esc. Chaco Lejos", "voto_valido": 38, "voto_blanco": 0, "voto_nulo": 0, "voto_emitido": 38, "validos": 1.0, "habilitados": 46, "ganador": 0.0263, "x": -64.9071, "y": -12.83958}, "2621.1": {"municipio": "80701", "recinto": "Esc. Puerto Ustarez", "voto_valido": 95, "voto_blanco": 1, "voto_nulo": 5, "voto_emitido": 101, "validos": 0.9406, "habilitados": 133, "ganador": 0.2105, "x": -64.45786, "y": -12.40728}, "2622.1": {"municipio": "80703", "recinto": "Esc. Alejandria", "voto_valido": 37, "voto_blanco": 0, "voto_nulo": 0, "voto_emitido": 37, "validos": 1.0, "habilitados": 52, "ganador": 0.027, "x": -65.06511, "y": -12.08011}, "2624.1": {"municipio": "80601", "recinto": "Esc. Perfecta Vda. De Bejarano", "voto_valido": 358, "voto_blanco": 4, "voto_nulo": 25, "voto_emitido": 387, "validos": 0.9251, "habilitados": 547, "ganador": 0.6369, "x": -64.76012, "y": -15.19398}, "2625.1": {"municipio": "80601", "recinto": "Esc. San Antonio", "voto_valido": 30, "voto_blanco": 0, "voto_nulo": 2, "voto_emitido": 32, "validos": 0.9375, "habilitados": 57, "ganador": 0.2333, "x": -64.99944, "y": -15.1992}, "2626.1": {"municipio": "80601", "recinto": "Esc. Camiaco", "voto_valido": 232, "voto_blanco": 4, "voto_nulo": 18, "voto_emitido": 254, "validos": 0.9134, "habilitados": 390, "ganador": 0.6164, "x": -64.86686, "y": -15.33278}, "2630.1": {"municipio": "80601", "recinto": "Esc. Gundonovia", "voto_valido": 89, "voto_blanco": 2, "voto_nulo": 10, "voto_emitido": 101, "validos": 0.8812, "habilitados": 157, "ganador": 0.6742, "x": -65.11512, "y": -15.51444}, "2631.1": {"municipio": "80601", "recinto": "Esc. Sachojere", "voto_valido": 291, "voto_blanco": 2, "voto_nulo": 13, "voto_emitido": 306, "validos": 0.951, "habilitados": 382, "ganador": 0.5567, "x": -64.75289, "y": -14.98731}, "2633.1": {"municipio": "80602", "recinto": "Esc. Humberto Velarde", "voto_valido": 193, "voto_blanco": 2, "voto_nulo": 6, "voto_emitido": 201, "validos": 0.9602, "habilitados": 267, "ganador": 0.6062, "x": -64.66631, "y": -15.02232}, "2634.1": {"municipio": "80602", "recinto": "Esc. Peroto", "voto_valido": 169, "voto_blanco": 2, "voto_nulo": 1, "voto_emitido": 172, "validos": 0.9826, "habilitados": 234, "ganador": 0.5325, "x": -64.63706, "y": -14.97516}, "2635.1": {"municipio": "80602", "recinto": "Esc.Villa Banzer", "voto_valido": 98, "voto_blanco": 2, "voto_nulo": 5, "voto_emitido": 105, "validos": 0.9333, "habilitados": 124, "ganador": 0.4694, "x": -64.41677, "y": -14.94876}, "2636.1": {"municipio": "80602", "recinto": "Esc. Santa Rosa", "voto_valido": 337, "voto_blanco": 8, "voto_nulo": 18, "voto_emitido": 363, "validos": 0.9284, "habilitados": 508, "ganador": 0.5223, "x": -64.244, "y": -15.10586}, "2637.2": {"municipio": "80602", "recinto": "Esc. Central 2 De Agosto", "voto_valido": 2142, "voto_blanco": 41, "voto_nulo": 176, "voto_emitido": 2359, "validos": 0.908, "habilitados": 3135, "ganador": 0.4608, "x": -63.86697, "y": -15.24271}, "2638.1": {"municipio": "80602", "recinto": "Esc. Caimanes", "voto_valido": 140, "voto_blanco": 2, "voto_nulo": 9, "voto_emitido": 151, "validos": 0.9272, "habilitados": 239, "ganador": 0.5429, "x": -64.05082, "y": -15.16342}, "2642.1": {"municipio": "80602", "recinto": "Esc. San Lorenzo", "voto_valido": 106, "voto_blanco": 1, "voto_nulo": 4, "voto_emitido": 111, "validos": 0.955, "habilitados": 148, "ganador": 0.4434, "x": -64.7207, "y": -15.03478}, "2643.1": {"municipio": "80602", "recinto": "Esc. Villa Alba", "voto_valido": 145, "voto_blanco": 0, "voto_nulo": 3, "voto_emitido": 148, "validos": 0.9797, "habilitados": 195, "ganador": 0.331, "x": -64.68153, "y": -15.06132}, "2644.1": {"municipio": "80801", "recinto": "U.E. Mcal. Jose Ballivian", "voto_valido": 1233, "voto_blanco": 13, "voto_nulo": 49, "voto_emitido": 1295, "validos": 0.9521, "habilitados": 1715, "ganador": 0.6723, "x": -64.05527, "y": -13.26313}, "2644.32118": {"municipio": "80801", "recinto": "U.E. Carmen Urdininea Rivero", "voto_valido": 1748, "voto_blanco": 7, "voto_nulo": 48, "voto_emitido": 1803, "validos": 0.9695, "habilitados": 2264, "ganador": 0.7145, "x": -64.05573, "y": -13.25852}, "2645.1": {"municipio": "80801", "recinto": "Esc. Angel Chavez Arza", "voto_valido": 114, "voto_blanco": 0, "voto_nulo": 5, "voto_emitido": 119, "validos": 0.958, "habilitados": 155, "ganador": 0.7632, "x": -64.24437, "y": -12.89689}, "2646.1": {"municipio": "80801", "recinto": "Esc. La Cayoba", "voto_valido": 90, "voto_blanco": 0, "voto_nulo": 2, "voto_emitido": 92, "validos": 0.9783, "habilitados": 131, "ganador": 0.7667, "x": -64.08502, "y": -13.09004}, "2647.1": {"municipio": "80801", "recinto": "Esc. Santa Maria", "voto_valido": 66, "voto_blanco": 0, "voto_nulo": 0, "voto_emitido": 66, "validos": 1.0, "habilitados": 81, "ganador": 0.7727, "x": -63.825, "y": -13.11831}, "2649.1": {"municipio": "80801", "recinto": "U.E. Cnel. Carmelo Cuellar J.", "voto_valido": 213, "voto_blanco": 2, "voto_nulo": 6, "voto_emitido": 221, "validos": 0.9638, "habilitados": 298, "ganador": 0.6479, "x": -63.79037, "y": -13.23383}, "2650.1": {"municipio": "80801", "recinto": "U.E. Macedonio Paz Pino", "voto_valido": 993, "voto_blanco": 8, "voto_nulo": 33, "voto_emitido": 1034, "validos": 0.9603, "habilitados": 1362, "ganador": 0.72, "x": -63.70535, "y": -13.27234}, "2651.1": {"municipio": "80802", "recinto": "U.E. Carmelo López", "voto_valido": 1129, "voto_blanco": 15, "voto_nulo": 26, "voto_emitido": 1170, "validos": 0.965, "habilitados": 1525, "ganador": 0.5926, "x": -63.6974, "y": -13.6553}, "2652.1": {"municipio": "80802", "recinto": "U.E. El Cairo", "voto_valido": 92, "voto_blanco": 0, "voto_nulo": 1, "voto_emitido": 93, "validos": 0.9892, "habilitados": 107, "ganador": 0.4674, "x": -63.72225, "y": -13.72575}, "2657.1": {"municipio": "80803", "recinto": "U.E. Juan Alberto Orellana", "voto_valido": 949, "voto_blanco": 6, "voto_nulo": 16, "voto_emitido": 971, "validos": 0.9773, "habilitados": 1414, "ganador": 0.588, "x": -63.87964, "y": -13.59328}, "2681.1": {"municipio": "80401", "recinto": "Esc. Wenceslao Añez", "voto_valido": 276, "voto_blanco": 2, "voto_nulo": 11, "voto_emitido": 289, "validos": 0.955, "habilitados": 382, "ganador": 0.5362, "x": -65.63189, "y": -14.60486}, "2683.1": {"municipio": "80602", "recinto": "Esc. Somopae", "voto_valido": 228, "voto_blanco": 4, "voto_nulo": 9, "voto_emitido": 241, "validos": 0.9461, "habilitados": 299, "ganador": 0.5219, "x": -64.65401, "y": -14.94441}, "2747.1": {"municipio": "80601", "recinto": "Esc. San Pablo Isiboro", "voto_valido": 119, "voto_blanco": 3, "voto_nulo": 11, "voto_emitido": 133, "validos": 0.8947, "habilitados": 197, "ganador": 0.8487, "x": -65.14317, "y": -15.70741}, "2748.1": {"municipio": "80602", "recinto": "Esc. Buen Jesus", "voto_valido": 316, "voto_blanco": 2, "voto_nulo": 17, "voto_emitido": 335, "validos": 0.9433, "habilitados": 423, "ganador": 0.2911, "x": -64.37089, "y": -14.98918}, "2749.1": {"municipio": "80201", "recinto": "U.E.   Warnes", "voto_valido": 372, "voto_blanco": 21, "voto_nulo": 57, "voto_emitido": 450, "validos": 0.8267, "habilitados": 578, "ganador": 0.5081, "x": -65.96947, "y": -10.92752}, "2784.10": {"municipio": "80202", "recinto": "U.E.  Alto de la Alianza", "voto_valido": 1531, "voto_blanco": 31, "voto_nulo": 83, "voto_emitido": 1645, "validos": 0.9307, "habilitados": 2170, "ganador": 0.4148, "x": -65.36181, "y": -10.82369}, "2784.11": {"municipio": "80202", "recinto": "U.E.   Los Almendros", "voto_valido": 1955, "voto_blanco": 22, "voto_nulo": 108, "voto_emitido": 2085, "validos": 0.9376, "habilitados": 2740, "ganador": 0.4931, "x": -65.3472, "y": -10.83402}, "2784.13": {"municipio": "80202", "recinto": "U.E.   Antonio Vaca Diez", "voto_valido": 1178, "voto_blanco": 12, "voto_nulo": 53, "voto_emitido": 1243, "validos": 0.9477, "habilitados": 1599, "ganador": 0.4211, "x": -65.35497, "y": -10.81294}, "2784.14": {"municipio": "80202", "recinto": "U.E.   Manuel Vicente Ballivian", "voto_valido": 478, "voto_blanco": 7, "voto_nulo": 34, "voto_emitido": 519, "validos": 0.921, "habilitados": 803, "ganador": 0.4519, "x": -65.35051, "y": -10.81116}, "2784.15": {"municipio": "80202", "recinto": "U.E. Miguel Antelo", "voto_valido": 470, "voto_blanco": 8, "voto_nulo": 25, "voto_emitido": 503, "validos": 0.9344, "habilitados": 665, "ganador": 0.4723, "x": -65.34438, "y": -10.82256}, "2784.16": {"municipio": "80202", "recinto": "U.E.   Brasil", "voto_valido": 1996, "voto_blanco": 23, "voto_nulo": 116, "voto_emitido": 2135, "validos": 0.9349, "habilitados": 2602, "ganador": 0.4093, "x": -65.3572, "y": -10.8307}, "2784.17": {"municipio": "80202", "recinto": "U.E. Belen", "voto_valido": 1015, "voto_blanco": 10, "voto_nulo": 51, "voto_emitido": 1076, "validos": 0.9433, "habilitados": 1391, "ganador": 0.4394, "x": -65.35558, "y": -10.83641}, "2784.18": {"municipio": "80202", "recinto": "U.E. Simón Bolívar", "voto_valido": 593, "voto_blanco": 6, "voto_nulo": 47, "voto_emitido": 646, "validos": 0.918, "habilitados": 840, "ganador": 0.4401, "x": -65.36375, "y": -10.83101}, "2784.19": {"municipio": "80202", "recinto": "(Cárcel) Penal Guayaramerin", "voto_valido": 106, "voto_blanco": 1, "voto_nulo": 7, "voto_emitido": 114, "validos": 0.9298, "habilitados": 178, "ganador": 0.4528, "x": -65.35279, "y": -10.81292}, "2784.25320": {"municipio": "80202", "recinto": "U.E. 9 de Abril", "voto_valido": 927, "voto_blanco": 15, "voto_nulo": 67, "voto_emitido": 1009, "validos": 0.9187, "habilitados": 1278, "ganador": 0.4261, "x": -65.36181, "y": -10.84011}, "2784.26359": {"municipio": "80202", "recinto": "U.E.  Mariscal Andres de Santa Cruz", "voto_valido": 1089, "voto_blanco": 16, "voto_nulo": 75, "voto_emitido": 1180, "validos": 0.9229, "habilitados": 1754, "ganador": 0.4233, "x": -65.35873, "y": -10.82093}, "2784.3": {"municipio": "80202", "recinto": "U.E.  Evangélico Nacional", "voto_valido": 1356, "voto_blanco": 18, "voto_nulo": 102, "voto_emitido": 1476, "validos": 0.9187, "habilitados": 1942, "ganador": 0.4115, "x": -65.35439, "y": -10.81791}, "2784.32115": {"municipio": "80202", "recinto": "U.E.  Guayaraguazu", "voto_valido": 434, "voto_blanco": 6, "voto_nulo": 20, "voto_emitido": 460, "validos": 0.9435, "habilitados": 771, "ganador": 0.4286, "x": -65.36192, "y": -10.80827}, "2784.5": {"municipio": "80202", "recinto": "U.E.  Manuel Antonio Ojopi", "voto_valido": 1364, "voto_blanco": 22, "voto_nulo": 73, "voto_emitido": 1459, "validos": 0.9349, "habilitados": 1906, "ganador": 0.4348, "x": -65.35567, "y": -10.81322}, "2784.6": {"municipio": "80202", "recinto": "U.E.  Elmer Botsford", "voto_valido": 595, "voto_blanco": 9, "voto_nulo": 20, "voto_emitido": 624, "validos": 0.9535, "habilitados": 805, "ganador": 0.4471, "x": -65.35297, "y": -10.8088}, "2784.7": {"municipio": "80202", "recinto": "U.E.  San Jose", "voto_valido": 1104, "voto_blanco": 15, "voto_nulo": 53, "voto_emitido": 1172, "validos": 0.942, "habilitados": 1468, "ganador": 0.4502, "x": -65.34554, "y": -10.81522}, "2784.8": {"municipio": "80202", "recinto": "U.E.  Mejillones", "voto_valido": 760, "voto_blanco": 8, "voto_nulo": 43, "voto_emitido": 811, "validos": 0.9371, "habilitados": 996, "ganador": 0.4737, "x": -65.35355, "y": -10.82544}, "2784.9": {"municipio": "80202", "recinto": "U.E.  6 de Junio", "voto_valido": 1605, "voto_blanco": 25, "voto_nulo": 85, "voto_emitido": 1715, "validos": 0.9359, "habilitados": 2157, "ganador": 0.4517, "x": -65.34737, "y": -10.82762}, "2785.1": {"municipio": "80202", "recinto": "Esc. Central San Lorenzo", "voto_valido": 99, "voto_blanco": 1, "voto_nulo": 4, "voto_emitido": 104, "validos": 0.9519, "habilitados": 143, "ganador": 0.5152, "x": -65.23228, "y": -11.73968}, "2786.1": {"municipio": "80304", "recinto": "Esc. Gualberto Villarruel", "voto_valido": 1224, "voto_blanco": 19, "voto_nulo": 112, "voto_emitido": 1355, "validos": 0.9033, "habilitados": 1789, "ganador": 0.5237, "x": -67.5281, "y": -14.44452}, "2786.26362": {"municipio": "80304", "recinto": "U.E. Melvin Jonnes", "voto_valido": 514, "voto_blanco": 12, "voto_nulo": 59, "voto_emitido": 585, "validos": 0.8786, "habilitados": 755, "ganador": 0.537, "x": -67.51963, "y": -14.43393}, "2786.3": {"municipio": "80304", "recinto": "Unidad Educativa Lucio Lens", "voto_valido": 1801, "voto_blanco": 20, "voto_nulo": 180, "voto_emitido": 2001, "validos": 0.9, "habilitados": 2947, "ganador": 0.4897, "x": -67.52292, "y": -14.44037}, "2786.32019": {"municipio": "80304", "recinto": "U.E. Filadelfia", "voto_valido": 944, "voto_blanco": 16, "voto_nulo": 85, "voto_emitido": 1045, "validos": 0.9033, "habilitados": 1437, "ganador": 0.5244, "x": -67.52394, "y": -14.43614}, "2786.32020": {"municipio": "80304", "recinto": "U.E. Obispo Juan Claudel Fe y Alegria", "voto_valido": 834, "voto_blanco": 10, "voto_nulo": 59, "voto_emitido": 903, "validos": 0.9236, "habilitados": 1255, "ganador": 0.4868, "x": -67.53003, "y": -14.4446}, "2786.4": {"municipio": "80304", "recinto": "Escuela Villa Lourdes", "voto_valido": 1238, "voto_blanco": 37, "voto_nulo": 121, "voto_emitido": 1396, "validos": 0.8868, "habilitados": 1819, "ganador": 0.483, "x": -67.5043, "y": -14.42944}, "2787.1": {"municipio": "80304", "recinto": "Esc. Central Nuevos Horizontes", "voto_valido": 430, "voto_blanco": 13, "voto_nulo": 79, "voto_emitido": 522, "validos": 0.8238, "habilitados": 688, "ganador": 0.4163, "x": -67.27888, "y": -14.59985}, "2788.1": {"municipio": "80302", "recinto": "Esc. Las Abras", "voto_valido": 93, "voto_blanco": 2, "voto_nulo": 3, "voto_emitido": 98, "validos": 0.949, "habilitados": 125, "ganador": 0.7742, "x": -66.93307, "y": -14.4615}, "2816.1": {"municipio": "80202", "recinto": "Esc. San Francisco Del Yata", "voto_valido": 59, "voto_blanco": 0, "voto_nulo": 3, "voto_emitido": 62, "validos": 0.9516, "habilitados": 80, "ganador": 0.4576, "x": -65.51111, "y": -10.61194}, "2824.1": {"municipio": "80501", "recinto": "Esc. Litoral", "voto_valido": 137, "voto_blanco": 3, "voto_nulo": 11, "voto_emitido": 151, "validos": 0.9073, "habilitados": 180, "ganador": 0.3066, "x": -65.57434, "y": -14.97235}, "2825.1": {"municipio": "80502", "recinto": "Esc. Retiro", "voto_valido": 96, "voto_blanco": 3, "voto_nulo": 14, "voto_emitido": 113, "validos": 0.8496, "habilitados": 137, "ganador": 0.3958, "x": -65.80604, "y": -15.34924}, "2827.1": {"municipio": "80501", "recinto": "Esc. Monte Mae", "voto_valido": 76, "voto_blanco": 0, "voto_nulo": 1, "voto_emitido": 77, "validos": 0.987, "habilitados": 110, "ganador": 0.5921, "x": -65.72498, "y": -15.53512}, "2885.1": {"municipio": "80301", "recinto": "Esc. San Marcos", "voto_valido": 19, "voto_blanco": 1, "voto_nulo": 2, "voto_emitido": 22, "validos": 0.8636, "habilitados": 34, "ganador": 0.2105, "x": -67.50578, "y": -13.81978}, "2886.1": {"municipio": "80502", "recinto": "Esc. Puerto San Borja", "voto_valido": 141, "voto_blanco": 5, "voto_nulo": 14, "voto_emitido": 160, "validos": 0.8812, "habilitados": 204, "ganador": 0.3404, "x": -65.79875, "y": -14.98267}, "3069.1": {"municipio": "80101", "recinto": "Escuela Casarabe", "voto_valido": 495, "voto_blanco": 3, "voto_nulo": 27, "voto_emitido": 525, "validos": 0.9429, "habilitados": 711, "ganador": 0.5657, "x": -64.47997, "y": -14.87161}, "3070.1": {"municipio": "80101", "recinto": "Escuela Iviato", "voto_valido": 259, "voto_blanco": 1, "voto_nulo": 2, "voto_emitido": 262, "validos": 0.9885, "habilitados": 348, "ganador": 0.7027, "x": -64.44854, "y": -14.83285}, "3072.1": {"municipio": "80602", "recinto": "Esc. Monte Cristo", "voto_valido": 59, "voto_blanco": 1, "voto_nulo": 0, "voto_emitido": 60, "validos": 0.9833, "habilitados": 91, "ganador": 0.5593, "x": -64.37403, "y": -15.61173}, "3073.1": {"municipio": "80602", "recinto": "Esc. La Isiga Persevera", "voto_valido": 21, "voto_blanco": 4, "voto_nulo": 1, "voto_emitido": 26, "validos": 0.8077, "habilitados": 56, "ganador": 0.5238, "x": -64.32283, "y": -15.39423}, "3074.1": {"municipio": "80302", "recinto": "Escuela El Oriente Del Yacuma", "voto_valido": 131, "voto_blanco": 2, "voto_nulo": 4, "voto_emitido": 137, "validos": 0.9562, "habilitados": 192, "ganador": 0.6489, "x": -66.99512, "y": -14.35404}, "3077.1": {"municipio": "80301", "recinto": "Esc. Buen Destino", "voto_valido": 82, "voto_blanco": 1, "voto_nulo": 21, "voto_emitido": 104, "validos": 0.7885, "habilitados": 188, "ganador": 0.3171, "x": -66.76987, "y": -11.76321}, "3078.1": {"municipio": "80301", "recinto": "Esc. Soraida", "voto_valido": 33, "voto_blanco": 0, "voto_nulo": 3, "voto_emitido": 36, "validos": 0.9167, "habilitados": 60, "ganador": 0.1818, "x": -67.50439, "y": -14.05581}, "3079.1": {"municipio": "80701", "recinto": "Esc. More Monte Azul", "voto_valido": 77, "voto_blanco": 0, "voto_nulo": 2, "voto_emitido": 79, "validos": 0.9747, "habilitados": 116, "ganador": 0.0779, "x": -64.91856, "y": -12.09472}, "3096.1": {"municipio": "80201", "recinto": "U.E. Bolívar", "voto_valido": 410, "voto_blanco": 24, "voto_nulo": 39, "voto_emitido": 473, "validos": 0.8668, "habilitados": 610, "ganador": 0.4024, "x": -65.9, "y": -11.00223}, "3097.1": {"municipio": "80201", "recinto": "Escuela 12 de Octubre", "voto_valido": 257, "voto_blanco": 12, "voto_nulo": 25, "voto_emitido": 294, "validos": 0.8741, "habilitados": 388, "ganador": 0.3891, "x": -65.69309, "y": -11.0167}, "3098.1": {"municipio": "80201", "recinto": "Escuela Mariposa", "voto_valido": 57, "voto_blanco": 1, "voto_nulo": 5, "voto_emitido": 63, "validos": 0.9048, "habilitados": 85, "ganador": 0.386, "x": -66.1415, "y": -12.27631}, "3099.1": {"municipio": "80201", "recinto": "Escuela Alto Ivon", "voto_valido": 419, "voto_blanco": 3, "voto_nulo": 134, "voto_emitido": 556, "validos": 0.7536, "habilitados": 695, "ganador": 0.2434, "x": -66.03656, "y": -11.87361}, "3100.1": {"municipio": "80201", "recinto": "Escuela Santuario", "voto_valido": 66, "voto_blanco": 1, "voto_nulo": 2, "voto_emitido": 69, "validos": 0.9565, "habilitados": 80, "ganador": 0.4242, "x": -66.4724, "y": -11.5389}, "3101.1": {"municipio": "80201", "recinto": "U.E. Santa Maria", "voto_valido": 307, "voto_blanco": 14, "voto_nulo": 40, "voto_emitido": 361, "validos": 0.8504, "habilitados": 486, "ganador": 0.4984, "x": -65.93813, "y": -11.1185}, "3102.1": {"municipio": "80402", "recinto": "Esc. Cooperativa", "voto_valido": 34, "voto_blanco": 0, "voto_nulo": 2, "voto_emitido": 36, "validos": 0.9444, "habilitados": 61, "ganador": 0.1765, "x": -65.04883, "y": -12.6354}, "3103.1": {"municipio": "80402", "recinto": "Escuela San Juan del Jordan", "voto_valido": 26, "voto_blanco": 0, "voto_nulo": 0, "voto_emitido": 26, "validos": 1.0, "habilitados": 101, "ganador": 0.3462, "x": -66.42942, "y": -12.88492}, "3105.1": {"municipio": "80601", "recinto": "Santa Rosa del Isiboro", "voto_valido": 102, "voto_blanco": 1, "voto_nulo": 9, "voto_emitido": 112, "validos": 0.9107, "habilitados": 175, "ganador": 0.8333, "x": -65.20737, "y": -16.26001}, "3106.1": {"municipio": "80502", "recinto": "Esc. San Jose Del Cabitu", "voto_valido": 184, "voto_blanco": 5, "voto_nulo": 25, "voto_emitido": 214, "validos": 0.8598, "habilitados": 276, "ganador": 0.4076, "x": -65.9744, "y": -15.26368}, "3108.1": {"municipio": "80501", "recinto": "Esc. San Antonio De Imose", "voto_valido": 34, "voto_blanco": 1, "voto_nulo": 13, "voto_emitido": 48, "validos": 0.7083, "habilitados": 125, "ganador": 0.7059, "x": -65.35487, "y": -15.95693}, "3110.1": {"municipio": "80501", "recinto": "Esc. Mercedes De Lojojota", "voto_valido": 129, "voto_blanco": 2, "voto_nulo": 14, "voto_emitido": 145, "validos": 0.8897, "habilitados": 224, "ganador": 0.8062, "x": -65.57259, "y": -16.5034}, "3113.1": {"municipio": "80602", "recinto": "Escuela 4 de Julio", "voto_valido": 159, "voto_blanco": 9, "voto_nulo": 35, "voto_emitido": 203, "validos": 0.7833, "habilitados": 282, "ganador": 0.3836, "x": -63.46377, "y": -15.73327}, "3125.1": {"municipio": "80101", "recinto": "Esc. Puerto Varador", "voto_valido": 559, "voto_blanco": 13, "voto_nulo": 67, "voto_emitido": 639, "validos": 0.8748, "habilitados": 824, "ganador": 0.5814, "x": -64.99762, "y": -14.87702}, "3126.2": {"municipio": "80102", "recinto": "Escuela Laguna Colorada", "voto_valido": 72, "voto_blanco": 1, "voto_nulo": 1, "voto_emitido": 74, "validos": 0.973, "habilitados": 96, "ganador": 0.3056, "x": -64.63057, "y": -14.63861}, "3127.1": {"municipio": "80501", "recinto": "Esc. Trinidacito", "voto_valido": 26, "voto_blanco": 1, "voto_nulo": 0, "voto_emitido": 27, "validos": 0.963, "habilitados": 51, "ganador": 0.6923, "x": -65.30994, "y": -15.76319}, "3129.1": {"municipio": "80801", "recinto": "Esc. San Borja Rio Blanco", "voto_valido": 149, "voto_blanco": 2, "voto_nulo": 4, "voto_emitido": 155, "validos": 0.9613, "habilitados": 211, "ganador": 0.6242, "x": -64.10181, "y": -12.62778}, "3130.1": {"municipio": "80803", "recinto": "U.E. Juan Antonio Velarde Guerra", "voto_valido": 61, "voto_blanco": 0, "voto_nulo": 2, "voto_emitido": 63, "validos": 0.9683, "habilitados": 74, "ganador": 0.5246, "x": -63.82495, "y": -13.6832}, "3173.1": {"municipio": "80702", "recinto": "Esc. El Carmen de Guacayane", "voto_valido": 50, "voto_blanco": 0, "voto_nulo": 0, "voto_emitido": 50, "validos": 1.0, "habilitados": 69, "ganador": 0.9, "x": -64.37999, "y": -13.12766}, "3174.1": {"municipio": "80802", "recinto": "U.E. Jasiaquiri", "voto_valido": 135, "voto_blanco": 1, "voto_nulo": 8, "voto_emitido": 144, "validos": 0.9375, "habilitados": 178, "ganador": 0.7852, "x": -63.7384, "y": -13.72094}, "3276.1": {"municipio": "80602", "recinto": "Escuela Elvira", "voto_valido": 240, "voto_blanco": 7, "voto_nulo": 25, "voto_emitido": 272, "validos": 0.8824, "habilitados": 342, "ganador": 0.4333, "x": -64.6015, "y": -14.9292}, "3316.1": {"municipio": "80601", "recinto": "Escuela Santa Rosa del Chapare", "voto_valido": 9, "voto_blanco": 0, "voto_nulo": 0, "voto_emitido": 9, "validos": 1.0, "habilitados": 35, "ganador": 0.8889, "x": -64.75722, "y": -15.93935}, "3340.1": {"municipio": "80102", "recinto": "Escuela Pedro Ignacio Muiba", "voto_valido": 229, "voto_blanco": 3, "voto_nulo": 10, "voto_emitido": 242, "validos": 0.9463, "habilitados": 399, "ganador": 0.7817, "x": -64.085, "y": -14.4919}, "3341.1": {"municipio": "80602", "recinto": "Escuela Nueva Magdalena", "voto_valido": 222, "voto_blanco": 3, "voto_nulo": 25, "voto_emitido": 250, "validos": 0.888, "habilitados": 356, "ganador": 0.2883, "x": -63.69876, "y": -15.48611}, "3384.1": {"municipio": "80301", "recinto": "Escuela De California", "voto_valido": 86, "voto_blanco": 3, "voto_nulo": 5, "voto_emitido": 94, "validos": 0.9149, "habilitados": 135, "ganador": 0.0581, "x": -66.90263, "y": -11.95482}, "3385.1": {"municipio": "80602", "recinto": "Escuela de Nueva Betania", "voto_valido": 297, "voto_blanco": 5, "voto_nulo": 17, "voto_emitido": 319, "validos": 0.931, "habilitados": 421, "ganador": 0.4141, "x": -64.34632, "y": -15.02995}, "3406.1": {"municipio": "80501", "recinto": "Escuela De Bermeo", "voto_valido": 66, "voto_blanco": 5, "voto_nulo": 20, "voto_emitido": 91, "validos": 0.7253, "habilitados": 119, "ganador": 0.2273, "x": -65.3772, "y": -14.89496}, "3516.1": {"municipio": "80301", "recinto": "Esc. San Jose", "voto_valido": 127, "voto_blanco": 1, "voto_nulo": 3, "voto_emitido": 131, "validos": 0.9695, "habilitados": 164, "ganador": 0.3071, "x": -67.37435, "y": -14.30772}, "3517.1": {"municipio": "80302", "recinto": "Esc. Tacuaral De Mattos", "voto_valido": 622, "voto_blanco": 8, "voto_nulo": 72, "voto_emitido": 702, "validos": 0.886, "habilitados": 799, "ganador": 0.8183, "x": -66.53598, "y": -14.99362}, "3518.1": {"municipio": "80302", "recinto": "Esc. Indigena Arenales", "voto_valido": 451, "voto_blanco": 14, "voto_nulo": 64, "voto_emitido": 529, "validos": 0.8526, "habilitados": 595, "ganador": 0.7184, "x": -66.9127, "y": -15.10867}, "3519.1": {"municipio": "80302", "recinto": "Esc. Mision Fatima", "voto_valido": 229, "voto_blanco": 3, "voto_nulo": 70, "voto_emitido": 302, "validos": 0.7583, "habilitados": 477, "ganador": 0.3406, "x": -66.746, "y": -15.45636}, "3520.1": {"municipio": "80304", "recinto": "Esc. Asuncion Del Quiquibey", "voto_valido": 134, "voto_blanco": 1, "voto_nulo": 20, "voto_emitido": 155, "validos": 0.8645, "habilitados": 201, "ganador": 0.4328, "x": -67.51161, "y": -14.64125}, "3521.1": {"municipio": "80402", "recinto": "Esc. Nueva Esperanza", "voto_valido": 31, "voto_blanco": 2, "voto_nulo": 2, "voto_emitido": 35, "validos": 0.8857, "habilitados": 45, "ganador": 0.6774, "x": -66.00737, "y": -12.97329}, "3522.1": {"municipio": "80402", "recinto": "Esc. Campo Ana Maria", "voto_valido": 30, "voto_blanco": 0, "voto_nulo": 1, "voto_emitido": 31, "validos": 0.9677, "habilitados": 39, "ganador": 0.5, "x": -65.57471, "y": -12.94433}, "3523.1": {"municipio": "80802", "recinto": "Esc. Alta Gracia", "voto_valido": 99, "voto_blanco": 3, "voto_nulo": 0, "voto_emitido": 102, "validos": 0.9706, "habilitados": 117, "ganador": 0.6667, "x": -63.66943, "y": -13.63675}, "3525.1": {"municipio": "80802", "recinto": "Esc. Cairo II", "voto_valido": 24, "voto_blanco": 0, "voto_nulo": 0, "voto_emitido": 24, "validos": 1.0, "habilitados": 28, "ganador": 0.2917, "x": -63.52425, "y": -14.20468}, "3676.1": {"municipio": "80301", "recinto": "Esc. Constanza Vargas", "voto_valido": 69, "voto_blanco": 0, "voto_nulo": 5, "voto_emitido": 74, "validos": 0.9324, "habilitados": 88, "ganador": 0.2609, "x": -66.73828, "y": -11.73581}, "3734.1": {"municipio": "80304", "recinto": "Esc. Playa Ancha", "voto_valido": 131, "voto_blanco": 12, "voto_nulo": 64, "voto_emitido": 207, "validos": 0.6329, "habilitados": 253, "ganador": 0.3053, "x": -67.26197, "y": -14.62954}, "3757.1": {"municipio": "80501", "recinto": "Esc. Oromomo", "voto_valido": 190, "voto_blanco": 5, "voto_nulo": 39, "voto_emitido": 234, "validos": 0.812, "habilitados": 422, "ganador": 0.8947, "x": -66.18743, "y": -16.04399}, "3867.1": {"municipio": "80102", "recinto": "U.E. La Curva", "voto_valido": 169, "voto_blanco": 4, "voto_nulo": 4, "voto_emitido": 177, "validos": 0.9548, "habilitados": 551, "ganador": 0.6154, "x": -64.2076, "y": -14.5887}, "3868.1": {"municipio": "80301", "recinto": "U.E. Carmen Alto", "voto_valido": 148, "voto_blanco": 1, "voto_nulo": 10, "voto_emitido": 159, "validos": 0.9308, "habilitados": 190, "ganador": 0.3108, "x": -66.36278, "y": -11.71022}, "3870.1": {"municipio": "80302", "recinto": "U.E. Quiquibey", "voto_valido": 232, "voto_blanco": 2, "voto_nulo": 38, "voto_emitido": 272, "validos": 0.8529, "habilitados": 342, "ganador": 0.6164, "x": -67.0975, "y": -15.36358}, "3871.1": {"municipio": "80302", "recinto": "U.E. Manguito", "voto_valido": 488, "voto_blanco": 5, "voto_nulo": 43, "voto_emitido": 536, "validos": 0.9104, "habilitados": 631, "ganador": 0.4508, "x": -66.63986, "y": -14.89842}, "3873.1": {"municipio": "80302", "recinto": "U.E. Marca Coroico", "voto_valido": 161, "voto_blanco": 11, "voto_nulo": 62, "voto_emitido": 234, "validos": 0.688, "habilitados": 287, "ganador": 0.7453, "x": -67.08862, "y": -14.78361}, "3875.1": {"municipio": "80501", "recinto": "U.E. San Bernardo", "voto_valido": 98, "voto_blanco": 4, "voto_nulo": 4, "voto_emitido": 106, "validos": 0.9245, "habilitados": 155, "ganador": 0.5102, "x": -65.2933, "y": -15.65132}, "3876.1": {"municipio": "80601", "recinto": "U.E. Palermo", "voto_valido": 43, "voto_blanco": 1, "voto_nulo": 1, "voto_emitido": 45, "validos": 0.9556, "habilitados": 49, "ganador": 0.907, "x": -64.97192, "y": -15.76694}, "3878.1": {"municipio": "80601", "recinto": "U.E. Villa El Carmen del Remanzo", "voto_valido": 58, "voto_blanco": 1, "voto_nulo": 10, "voto_emitido": 69, "validos": 0.8406, "habilitados": 124, "ganador": 0.5862, "x": -65.00182, "y": -15.25932}, "4003.25317": {"municipio": "80201", "recinto": "U.E. La Esperanza", "voto_valido": 387, "voto_blanco": 13, "voto_nulo": 43, "voto_emitido": 443, "validos": 0.8736, "habilitados": 557, "ganador": 0.522, "x": -66.0544, "y": -11.06529}, "4004.25318": {"municipio": "80201", "recinto": "U.E. Popechi", "voto_valido": 296, "voto_blanco": 17, "voto_nulo": 16, "voto_emitido": 329, "validos": 0.8997, "habilitados": 438, "ganador": 0.4561, "x": -66.07247, "y": -11.13074}, "4005.25319": {"municipio": "80201", "recinto": "U.E. Bella Flor", "voto_valido": 188, "voto_blanco": 3, "voto_nulo": 14, "voto_emitido": 205, "validos": 0.9171, "habilitados": 280, "ganador": 0.3723, "x": -66.21178, "y": -11.33017}, "4115.25525": {"municipio": "80602", "recinto": "U.E. Canaan", "voto_valido": 250, "voto_blanco": 5, "voto_nulo": 28, "voto_emitido": 283, "validos": 0.8834, "habilitados": 457, "ganador": 0.284, "x": -63.49511, "y": -15.68934}, "4117.1": {"municipio": "80402", "recinto": "U.E. Las Abras De Yacuma", "voto_valido": 43, "voto_blanco": 0, "voto_nulo": 2, "voto_emitido": 45, "validos": 0.9556, "habilitados": 243, "ganador": 0.3953, "x": -65.41503, "y": -12.3666}, "4171.25566": {"municipio": "80304", "recinto": "U.E. Collana Linares", "voto_valido": 466, "voto_blanco": 12, "voto_nulo": 117, "voto_emitido": 595, "validos": 0.7832, "habilitados": 761, "ganador": 0.3176, "x": -67.21294, "y": -14.70107}, "4172.25567": {"municipio": "80102", "recinto": "U.E. Villa Rodeo", "voto_valido": 51, "voto_blanco": 2, "voto_nulo": 2, "voto_emitido": 55, "validos": 0.9273, "habilitados": 134, "ganador": 0.5686, "x": -64.27238, "y": -14.55108}, "4230.25862": {"municipio": "80302", "recinto": "U.E. Galilea", "voto_valido": 537, "voto_blanco": 13, "voto_nulo": 50, "voto_emitido": 600, "validos": 0.895, "habilitados": 734, "ganador": 0.5754, "x": -66.681, "y": -14.877}, "4231.25863": {"municipio": "80302", "recinto": "U.E. Cooperativa Chimane", "voto_valido": 234, "voto_blanco": 6, "voto_nulo": 40, "voto_emitido": 280, "validos": 0.8357, "habilitados": 311, "ganador": 0.3077, "x": -67.034, "y": -15.163}, "4232.25864": {"municipio": "80304", "recinto": "U.E. Bajo Colorado", "voto_valido": 334, "voto_blanco": 14, "voto_nulo": 88, "voto_emitido": 436, "validos": 0.7661, "habilitados": 507, "ganador": 0.3922, "x": -67.117, "y": -14.881}, "4233.25865": {"municipio": "80301", "recinto": "U.E. Gualaguagua", "voto_valido": 57, "voto_blanco": 0, "voto_nulo": 4, "voto_emitido": 61, "validos": 0.9344, "habilitados": 68, "ganador": 0.0877, "x": -67.28342, "y": -14.34362}, "4234.25866": {"municipio": "80301", "recinto": "U.E. Ratije", "voto_valido": 88, "voto_blanco": 2, "voto_nulo": 1, "voto_emitido": 91, "validos": 0.967, "habilitados": 116, "ganador": 0.2159, "x": -67.18024, "y": -14.13151}, "4358.26060": {"municipio": "80501", "recinto": "U.E. San José del Secure", "voto_valido": 76, "voto_blanco": 1, "voto_nulo": 17, "voto_emitido": 94, "validos": 0.8085, "habilitados": 130, "ganador": 0.5658, "x": -65.92781, "y": -15.91319}, "4418.26175": {"municipio": "80302", "recinto": "U.E. Cosincho", "voto_valido": 328, "voto_blanco": 0, "voto_nulo": 63, "voto_emitido": 391, "validos": 0.8389, "habilitados": 443, "ganador": 0.7165, "x": -66.82509, "y": -15.36304}, "4419.26176": {"municipio": "80201", "recinto": "U.E. Recreo", "voto_valido": 101, "voto_blanco": 7, "voto_nulo": 9, "voto_emitido": 117, "validos": 0.8632, "habilitados": 130, "ganador": 0.4455, "x": -66.38955, "y": -11.66046}, "4420.26177": {"municipio": "80201", "recinto": "U.E. 23 de Marzo", "voto_valido": 135, "voto_blanco": 8, "voto_nulo": 6, "voto_emitido": 149, "validos": 0.906, "habilitados": 179, "ganador": 0.5407, "x": -66.70159, "y": -11.67328}, "4421.26178": {"municipio": "80304", "recinto": "U.E. El Cebu", "voto_valido": 172, "voto_blanco": 13, "voto_nulo": 37, "voto_emitido": 222, "validos": 0.7748, "habilitados": 289, "ganador": 0.5581, "x": -67.45091, "y": -14.46265}, "4422.26179": {"municipio": "80602", "recinto": "U.E. Unión y Fe", "voto_valido": 176, "voto_blanco": 11, "voto_nulo": 13, "voto_emitido": 200, "validos": 0.88, "habilitados": 268, "ganador": 0.4545, "x": -64.19151, "y": -15.10833}, "4486.32117": {"municipio": "80402", "recinto": "U.E. Bienvenido", "voto_valido": 49, "voto_blanco": 0, "voto_nulo": 0, "voto_emitido": 49, "validos": 1.0, "habilitados": 179, "ganador": 0.5102, "x": -65.51171, "y": -12.66647}, "4509.32144": {"municipio": "80201", "recinto": "U.E. Los Cayuses", "voto_valido": 45, "voto_blanco": 1, "voto_nulo": 5, "voto_emitido": 51, "validos": 0.8824, "habilitados": 77, "ganador": 0.5556, "x": -66.19313, "y": -12.11882}, "4576.32286": {"municipio": "80201", "recinto": "U.E. Nueva Unión I", "voto_valido": 118, "voto_blanco": 3, "voto_nulo": 10, "voto_emitido": 131, "validos": 0.9008, "habilitados": 153, "ganador": 0.322, "x": -66.01481, "y": -11.05501}, "4579.32291": {"municipio": "80401", "recinto": "U.E. Carmen del Matto", "voto_valido": 54, "voto_blanco": 0, "voto_nulo": 0, "voto_emitido": 54, "validos": 1.0, "habilitados": 66, "ganador": 0.7963, "x": -66.07293, "y": -14.73662}, "4595.32337": {"municipio": "80501", "recinto": "U.E. San Mateo de San Ramoncito", "voto_valido": 46, "voto_blanco": 2, "voto_nulo": 3, "voto_emitido": 51, "validos": 0.902, "habilitados": 67, "ganador": 0.6087, "x": -65.51017, "y": -16.23686}}